deltadb/__init__.py
deltadb/delta.py
deltadb/magic.py
deltadb-0.1.8.dist-info/LICENSE
deltadb-0.1.8.dist-info/METADATA
deltadb-0.1.8.dist-info/WHEEL
deltadb-0.1.8.dist-info/RECORD
