Metadata-Version: 2.1
Name: deltadb
Version: 0.1.8
Summary: 
Author: uname-n
Author-email: noreply@github.com
Requires-Python: >=3.12,<4.0
Classifier: Programming Language :: Python :: 3
Classifier: Programming Language :: Python :: 3.12
Requires-Dist: deltalake (>=0.18.2,<0.19.0)
Requires-Dist: ipython (>=8.26.0,<9.0.0)
Requires-Dist: polars (>=1.4.1,<2.0.0)
